prng.sv
module prng (
    input logic clk,
    input logic reset,
    output logic [9:0] prng_out
);
assign prng_out = 250;



endmodule

position.sv
module position # (
    parameter logic [9:0] PIPE_GAP = 100,
    parameter logic [9:0] PIPE_X_START = 640,
    parameter logic [9:0] BIRD_X = 100
)(
    input logic clk,
    input logic reset,
    input logic start_button,
    input logic [9:0] bird_y,
    input logic collided,
	 input logic enable,

    output logic [9:0] pipe_x,
    output logic [9:0] pipe_y_top,
    output logic [9:0] pipe_y_bot,
	 output logic led1,
	 output logic led2,
	 output logic led3,
	 
	 
	 
	 output logic [1:0] state
);

logic [9:0] pipe_y_start;

prng pipe_y_height (
    .clk(clk),
    .reset(reset),
    .prng_out(pipe_y_start)
);

// State machine
localparam logic [1:0] STATE_IDLE = 2'b00;
localparam logic [1:0] STATE_PLAY = 2'b01;
localparam logic [1:0] STATE_GAME_OVER = 2'b10;

//logic [1:0] state;
logic [1:0] next_state;

logic [9:0] pipe_y;
logic [9:0] pipe_y_next;
logic [9:0] pipe_x_next;

assign led1 = (state == STATE_IDLE);
assign led2 = (state == STATE_PLAY);
assign led3 = (state == STATE_GAME_OVER);


always_ff @(posedge clk or posedge reset) begin
    if (reset) begin
        state <= STATE_IDLE;
    end
    else begin
		  state <= next_state;
    end
end
assign pipe_y_bot = pipe_y + PIPE_GAP;
assign pipe_y_top = pipe_y - PIPE_GAP;


always_ff @(posedge enable or posedge reset) begin // TODO: Make synchronous
    if (reset) begin
        pipe_x <= PIPE_X_START;
        pipe_y <= pipe_y_start;
    end else begin
        pipe_x <= pipe_x_next;
        pipe_y <= pipe_y_next;
    end

end


always_comb begin
    case (state)
        STATE_IDLE: begin
            if (start_button) begin
                next_state = STATE_PLAY;
            end else begin
					next_state = STATE_IDLE;
				end
            pipe_x_next = PIPE_X_START;
            pipe_y_next = pipe_y_start;
        end
        STATE_PLAY: begin
            if (collided) begin
                next_state = STATE_GAME_OVER;
            end else begin
                next_state = STATE_PLAY;
            end
            pipe_x_next = pipe_x - 10'd20;
            pipe_y_next = pipe_y;
        end
        STATE_GAME_OVER: begin
            if (reset) begin
                next_state = STATE_IDLE;
            end else begin
						next_state = STATE_GAME_OVER;
				end
				pipe_x_next = pipe_x;
				pipe_y_next = pipe_y;
        end
        default: begin
				pipe_x_next = pipe_x;
				pipe_y_next = pipe_y;
				next_state = STATE_IDLE;
		  end
    endcase
end
endmodule

collision.sv
module collision (
    input logic [9:0] bird_x,
    input logic [9:0] bird_y,
    input logic [9:0] bird_width,
    input logic [9:0] bird_height,
    input logic [9:0] pipe_x,
    input logic [9:0] pipe_width,
	 input logic [9:0] pipe_height,
    input logic [9:0] pipe_y_top,
    input logic [9:0] pipe_y_bot,

    output logic collided
);

logic [9:0] bird_bot;
logic [9:0] bird_top;
logic [9:0] bird_left;
logic [9:0] bird_right;

logic [9:0] pipe_bot;
logic [9:0] pipe_top;
logic [9:0] pipe_left;
logic [9:0] pipe_right;

assign bird_bot = bird_y + bird_height;
assign bird_top = bird_y - bird_height;
assign bird_left = bird_x - bird_width;
assign bird_right = bird_x + bird_width;

assign pipe_bot = pipe_y_bot + pipe_height;
assign pipe_top = pipe_y_top - pipe_height;
assign pipe_left = pipe_x - pipe_width;
assign pipe_right = pipe_x + pipe_width;

always_comb begin
    if ((bird_bot > pipe_bot || bird_top < pipe_top) && ((pipe_left < bird_right && bird_right < pipe_right) || (pipe_left < bird_left && bird_left < pipe_right))) begin
        collided = 1;
    end else begin
        collided = 0;
    end
end 

endmodule

position_tb.sv
module position_tb (
	 output logic clk,
    output logic reset,
    output logic start_button,
	 output logic [9:0] bird_x,
    output logic [9:0] bird_y,
    output logic collided,
    output logic enable,

    output logic [9:0] pipe_x,
    output logic [9:0] pipe_y_top,
    output logic [9:0] pipe_y_bot,
	 output logic led1,
	 output logic led2,
	 output logic led3,
	 
	 output logic [1:0] state
);

assign bird_x = 100;
assign bird_y = 250;

collision collision_inst (
    // Input
    .bird_x(100),
    .bird_y(bird_y),
    .bird_width(20),
    .bird_height(20),
    .pipe_x(pipe_x),
    .pipe_width(50),
	 .pipe_height(50),
    .pipe_y_top(pipe_y_top),
    .pipe_y_bot(pipe_y_bot),

    // Output
    .collided(collided)
);

position position_inst (
    // Input
    .clk(clk),
    .reset(reset),
    .start_button(start_button),
    .bird_y(bird_y),
    .collided(collided),
	 .enable(enable),

    // Output
    .pipe_x(pipe_x),
    .pipe_y_top(pipe_y_top),
    .pipe_y_bot(pipe_y_bot),
	 .led1(led1),
	 .led2(led2),
	 .led3(led3),
	 .state(state)
);


initial begin
	clk = 1;
	for (integer i = 0; i < 250; i++) begin
		#1;
		clk = 0;
		#1;
		clk = 1;
	end

end
initial begin
	enable = 1;
	for (integer i = 0; i < 250; i++) begin
		#4;
		enable = 0;
		#4;
		enable = 1;
	end
end


initial begin
	$dumpfile("position_tb.vcd");	
	$dumpvars(0, position_tb);
	reset = 1;
	start_button = 0;
	#2;
	reset = 0;
	#4;
	start_button = 1;
	#2;
	start_button = 0;
	#230;
end

endmodule

position_tb.vcd
$date
	Fri May  9 14:22:37 2025
$end
$version
	Icarus Verilog
$end
$timescale
	1s
$end
$scope module position_tb $end
$var wire 10 ! bird_x [9:0] $end
$var wire 10 " bird_y [9:0] $end
$var wire 2 # state [1:0] $end
$var wire 10 $ pipe_y_top [9:0] $end
$var wire 10 % pipe_y_bot [9:0] $end
$var wire 10 & pipe_x [9:0] $end
$var wire 1 ' led3 $end
$var wire 1 ( led2 $end
$var wire 1 ) led1 $end
$var wire 1 * collided $end
$var reg 1 + clk $end
$var reg 1 , enable $end
$var reg 1 - reset $end
$var reg 1 . start_button $end
$scope module collision_inst $end
$var wire 10 / bird_height [9:0] $end
$var wire 10 0 bird_width [9:0] $end
$var wire 10 1 bird_x [9:0] $end
$var wire 10 2 bird_y [9:0] $end
$var wire 10 3 pipe_height [9:0] $end
$var wire 10 4 pipe_width [9:0] $end
$var wire 10 5 pipe_y_top [9:0] $end
$var wire 10 6 pipe_y_bot [9:0] $end
$var wire 10 7 pipe_x [9:0] $end
$var wire 10 8 pipe_top [9:0] $end
$var wire 10 9 pipe_right [9:0] $end
$var wire 10 : pipe_left [9:0] $end
$var wire 10 ; pipe_bot [9:0] $end
$var wire 10 < bird_top [9:0] $end
$var wire 10 = bird_right [9:0] $end
$var wire 10 > bird_left [9:0] $end
$var wire 10 ? bird_bot [9:0] $end
$var reg 1 * collided $end
$upscope $end
$scope module position_inst $end
$var wire 10 @ bird_y [9:0] $end
$var wire 1 + clk $end
$var wire 1 * collided $end
$var wire 1 , enable $end
$var wire 10 A pipe_y_start [9:0] $end
$var wire 1 - reset $end
$var wire 1 . start_button $end
$var wire 10 B pipe_y_top [9:0] $end
$var wire 10 C pipe_y_bot [9:0] $end
$var wire 1 ' led3 $end
$var wire 1 ( led2 $end
$var wire 1 ) led1 $end
$var parameter 10 D BIRD_X $end
$var parameter 10 E PIPE_GAP $end
$var parameter 10 F PIPE_X_START $end
$var parameter 2 G STATE_GAME_OVER $end
$var parameter 2 H STATE_IDLE $end
$var parameter 2 I STATE_PLAY $end
$var reg 2 J next_state [1:0] $end
$var reg 10 K pipe_x [9:0] $end
$var reg 10 L pipe_x_next [9:0] $end
$var reg 10 M pipe_y [9:0] $end
$var reg 10 N pipe_y_next [9:0] $end
$var reg 2 O state [1:0] $end
$scope module pipe_y_height $end
$var wire 1 + clk $end
$var wire 10 P prng_out [9:0] $end
$var wire 1 - reset $end
$upscope $end
$upscope $end
$scope begin $ivl_for_loop0 $end
$var integer 32 Q i [31:0] $end
$upscope $end
$scope begin $ivl_for_loop1 $end
$var integer 32 R i [31:0] $end
$upscope $end
$upscope $end
$enddefinitions $end
$comment Show the parameter values. $end
$dumpall
b1 I
b0 H
b10 G
b1010000000 F
b1100100 E
b1100100 D
$end
#0
$dumpvars
b0 R
b0 Q
b11111010 P
b0 O
b11111010 N
b11111010 M
b1010000000 L
b1010000000 K
b0 J
b101011110 C
b10010110 B
b11111010 A
b11111010 @
b100001110 ?
b1010000 >
b1111000 =
b11100110 <
b110010000 ;
b1001001110 :
b1010110010 9
b1100100 8
b1010000000 7
b101011110 6
b10010110 5
b110010 4
b110010 3
b11111010 2
b1100100 1
b10100 0
b10100 /
0.
1-
1,
1+
0*
1)
0(
0'
b1010000000 &
b101011110 %
b10010110 $
b0 #
b11111010 "
b1100100 !
$end
#1
0+
#2
b1 Q
1+
0-
#3
0+
#4
b10 Q
1+
0,
#5
0+
#6
b1001101100 L
0)
1(
b1 #
b1 O
b1 J
b11 Q
1+
1.
#7
0+
#8
b1001011000 L
b1010011110 9
b1000111010 :
b1001101100 &
b1001101100 7
b1001101100 K
b100 Q
1+
0.
b1 R
1,
#9
0+
#10
b101 Q
1+
#11
0+
#12
b110 Q
1+
0,
#13
0+
#14
b111 Q
1+
#15
0+
#16
b1001000100 L
b1010001010 9
b1000100110 :
b1001011000 &
b1001011000 7
b1001011000 K
b1000 Q
1+
b10 R
1,
#17
0+
#18
b1001 Q
1+
#19
0+
#20
b1010 Q
1+
0,
#21
0+
#22
b1011 Q
1+
#23
0+
#24
b1000110000 L
b1001110110 9
b1000010010 :
b1001000100 &
b1001000100 7
b1001000100 K
b1100 Q
1+
b11 R
1,
#25
0+
#26
b1101 Q
1+
#27
0+
#28
b1110 Q
1+
0,
#29
0+
#30
b1111 Q
1+
#31
0+
#32
b1000011100 L
b1001100010 9
b111111110 :
b1000110000 &
b1000110000 7
b1000110000 K
b10000 Q
1+
b100 R
1,
#33
0+
#34
b10001 Q
1+
#35
0+
#36
b10010 Q
1+
0,
#37
0+
#38
b10011 Q
1+
#39
0+
#40
b1000001000 L
b1001001110 9
b111101010 :
b1000011100 &
b1000011100 7
b1000011100 K
b10100 Q
1+
b101 R
1,
#41
0+
#42
b10101 Q
1+
#43
0+
#44
b10110 Q
1+
0,
#45
0+
#46
b10111 Q
1+
#47
0+
#48
b111110100 L
b1000111010 9
b111010110 :
b1000001000 &
b1000001000 7
b1000001000 K
b11000 Q
1+
b110 R
1,
#49
0+
#50
b11001 Q
1+
#51
0+
#52
b11010 Q
1+
0,
#53
0+
#54
b11011 Q
1+
#55
0+
#56
b111100000 L
b1000100110 9
b111000010 :
b111110100 &
b111110100 7
b111110100 K
b11100 Q
1+
b111 R
1,
#57
0+
#58
b11101 Q
1+
#59
0+
#60
b11110 Q
1+
0,
#61
0+
#62
b11111 Q
1+
#63
0+
#64
b111001100 L
b1000010010 9
b110101110 :
b111100000 &
b111100000 7
b111100000 K
b100000 Q
1+
b1000 R
1,
#65
0+
#66
b100001 Q
1+
#67
0+
#68
b100010 Q
1+
0,
#69
0+
#70
b100011 Q
1+
#71
0+
#72
b110111000 L
b111111110 9
b110011010 :
b111001100 &
b111001100 7
b111001100 K
b100100 Q
1+
b1001 R
1,
#73
0+
#74
b100101 Q
1+
#75
0+
#76
b100110 Q
1+
0,
#77
0+
#78
b100111 Q
1+
#79
0+
#80
b110100100 L
b111101010 9
b110000110 :
b110111000 &
b110111000 7
b110111000 K
b101000 Q
1+
b1010 R
1,
#81
0+
#82
b101001 Q
1+
#83
0+
#84
b101010 Q
1+
0,
#85
0+
#86
b101011 Q
1+
#87
0+
#88
b110010000 L
b111010110 9
b101110010 :
b110100100 &
b110100100 7
b110100100 K
b101100 Q
1+
b1011 R
1,
#89
0+
#90
b101101 Q
1+
#91
0+
#92
b101110 Q
1+
0,
#93
0+
#94
b101111 Q
1+
#95
0+
#96
b101111100 L
b111000010 9
b101011110 :
b110010000 &
b110010000 7
b110010000 K
b110000 Q
1+
b1100 R
1,
#97
0+
#98
b110001 Q
1+
#99
0+
#100
b110010 Q
1+
0,
#101
0+
#102
b110011 Q
1+
#103
0+
#104
b101101000 L
b110101110 9
b101001010 :
b101111100 &
b101111100 7
b101111100 K
b110100 Q
1+
b1101 R
1,
#105
0+
#106
b110101 Q
1+
#107
0+
#108
b110110 Q
1+
0,
#109
0+
#110
b110111 Q
1+
#111
0+
#112
b101010100 L
b110011010 9
b100110110 :
b101101000 &
b101101000 7
b101101000 K
b111000 Q
1+
b1110 R
1,
#113
0+
#114
b111001 Q
1+
#115
0+
#116
b111010 Q
1+
0,
#117
0+
#118
b111011 Q
1+
#119
0+
#120
b101000000 L
b110000110 9
b100100010 :
b101010100 &
b101010100 7
b101010100 K
b111100 Q
1+
b1111 R
1,
#121
0+
#122
b111101 Q
1+
#123
0+
#124
b111110 Q
1+
0,
#125
0+
#126
b111111 Q
1+
#127
0+
#128
b100101100 L
b101110010 9
b100001110 :
b101000000 &
b101000000 7
b101000000 K
b1000000 Q
1+
b10000 R
1,
#129
0+
#130
b1000001 Q
1+
#131
0+
#132
b1000010 Q
1+
0,
#133
0+
#134
b1000011 Q
1+
#135
0+
#136
b100011000 L
b101011110 9
b11111010 :
b100101100 &
b100101100 7
b100101100 K
b1000100 Q
1+
b10001 R
1,
#137
0+
#138
b1000101 Q
1+
#139
0+
#140
b1000110 Q
1+
0,
#141
0+
#142
b1000111 Q
1+
#143
0+
#144
b100000100 L
b101001010 9
b11100110 :
b100011000 &
b100011000 7
b100011000 K
b1001000 Q
1+
b10010 R
1,
#145
0+
#146
b1001001 Q
1+
#147
0+
#148
b1001010 Q
1+
0,
#149
0+
#150
b1001011 Q
1+
#151
0+
#152
b11110000 L
b100110110 9
b11010010 :
b100000100 &
b100000100 7
b100000100 K
b1001100 Q
1+
b10011 R
1,
#153
0+
#154
b1001101 Q
1+
#155
0+
#156
b1001110 Q
1+
0,
#157
0+
#158
b1001111 Q
1+
#159
0+
#160
b11011100 L
b100100010 9
b10111110 :
b11110000 &
b11110000 7
b11110000 K
b1010000 Q
1+
b10100 R
1,
#161
0+
#162
b1010001 Q
1+
#163
0+
#164
b1010010 Q
1+
0,
#165
0+
#166
b1010011 Q
1+
#167
0+
#168
b11001000 L
b100001110 9
b10101010 :
b11011100 &
b11011100 7
b11011100 K
b1010100 Q
1+
b10101 R
1,
#169
0+
#170
b1010101 Q
1+
#171
0+
#172
b1010110 Q
1+
0,
#173
0+
#174
b1010111 Q
1+
#175
0+
#176
b10110100 L
b11111010 9
b10010110 :
b11001000 &
b11001000 7
b11001000 K
b1011000 Q
1+
b10110 R
1,
#177
0+
#178
b1011001 Q
1+
#179
0+
#180
b1011010 Q
1+
0,
#181
0+
#182
b1011011 Q
1+
#183
0+
#184
b10100000 L
b11100110 9
b10000010 :
b10110100 &
b10110100 7
b10110100 K
b1011100 Q
1+
b10111 R
1,
#185
0+
#186
b1011101 Q
1+
#187
0+
#188
b1011110 Q
1+
0,
#189
0+
#190
b1011111 Q
1+
#191
0+
#192
b10001100 L
b11010010 9
b1101110 :
b10100000 &
b10100000 7
b10100000 K
b1100000 Q
1+
b11000 R
1,
#193
0+
#194
b1100001 Q
1+
#195
0+
#196
b1100010 Q
1+
0,
#197
0+
#198
b1100011 Q
1+
#199
0+
#200
b1111000 L
b10111110 9
b1011010 :
b10001100 &
b10001100 7
b10001100 K
b1100100 Q
1+
b11001 R
1,
#201
0+
#202
b1100101 Q
1+
#203
0+
#204
b1100110 Q
1+
0,
#205
0+
#206
b1100111 Q
1+
#207
0+
#208
b1100100 L
b10101010 9
b1000110 :
b1111000 &
b1111000 7
b1111000 K
b1101000 Q
1+
b11010 R
1,
#209
0+
#210
b1101001 Q
1+
#211
0+
#212
b1101010 Q
1+
0,
#213
0+
#214
b1101011 Q
1+
#215
0+
#216
b1010000 L
b10010110 9
b110010 :
b1100100 &
b1100100 7
b1100100 K
b1101100 Q
1+
b11011 R
1,
#217
0+
#218
b1101101 Q
1+
#219
0+
#220
b1101110 Q
1+
0,
#221
0+
#222
b1101111 Q
1+
#223
0+
#224
b111100 L
b10000010 9
b11110 :
b1010000 &
b1010000 7
b1010000 K
b1110000 Q
1+
b11100 R
1,
#225
0+
#226
b1110001 Q
1+
#227
0+
#228
b1110010 Q
1+
0,
#229
0+
#230
b1110011 Q
1+
#231
0+
#232
b101000 L
b1101110 9
b1010 :
b111100 &
b111100 7
b111100 K
b1110100 Q
1+
b11101 R
1,
#233
0+
#234
b1110101 Q
1+
#235
0+
#236
b1110110 Q
1+
0,
#237
0+
#238
b1110111 Q
1+
#239
0+
#240
b10100 L
b1011010 9
b1111110110 :
b101000 &
b101000 7
b101000 K
b1111000 Q
1+
b11110 R
1,
#241
0+
#242
b1111001 Q
1+
#243
0+
#244
b1111010 Q
1+
0,
#245
0+
#246
b1111011 Q
1+
#247
0+
#248
b0 L
b1000110 9
b1111100010 :
b10100 &
b10100 7
b10100 K
b1111100 Q
1+
b11111 R
1,
#249
0+
#250
b1111101 Q
1+
#251
0+
#252
b1111110 Q
1+
0,
#253
0+
#254
b1111111 Q
1+
#255
0+
#256
b1111101100 L
b110010 9
b1111001110 :
b0 &
b0 7
b0 K
b10000000 Q
1+
b100000 R
1,
#257
0+
#258
b10000001 Q
1+
#259
0+
#260
b10000010 Q
1+
0,
#261
0+
#262
b10000011 Q
1+
#263
0+
#264
b1111011000 L
b11110 9
b1110111010 :
b1111101100 &
b1111101100 7
b1111101100 K
b10000100 Q
1+
b100001 R
1,
#265
0+
#266
b10000101 Q
1+
#267
0+
#268
b10000110 Q
1+
0,
#269
0+
#270
b10000111 Q
1+
#271
0+
#272
b1111000100 L
b1010 9
b1110100110 :
b1111011000 &
b1111011000 7
b1111011000 K
b10001000 Q
1+
b100010 R
1,
#273
0+
#274
b10001001 Q
1+
#275
0+
#276
b10001010 Q
1+
0,
#277
0+
#278
b10001011 Q
1+
#279
0+
#280
b1110110000 L
b1111110110 9
b1110010010 :
b1111000100 &
b1111000100 7
b1111000100 K
b10001100 Q
1+
b100011 R
1,
#281
0+
#282
b10001101 Q
1+
#283
0+
#284
b10001110 Q
1+
0,
#285
0+
#286
b10001111 Q
1+
#287
0+
#288
b1110011100 L
b1111100010 9
b1101111110 :
b1110110000 &
b1110110000 7
b1110110000 K
b10010000 Q
1+
b100100 R
1,
#289
0+
#290
b10010001 Q
1+
#291
0+
#292
b10010010 Q
1+
0,
#293
0+
#294
b10010011 Q
1+
#295
0+
#296
b1110001000 L
b1111001110 9
b1101101010 :
b1110011100 &
b1110011100 7
b1110011100 K
b10010100 Q
1+
b100101 R
1,
#297
0+
#298
b10010101 Q
1+
#299
0+
#300
b10010110 Q
1+
0,
#301
0+
#302
b10010111 Q
1+
#303
0+
#304
b1101110100 L
b1110111010 9
b1101010110 :
b1110001000 &
b1110001000 7
b1110001000 K
b10011000 Q
1+
b100110 R
1,
#305
0+
#306
b10011001 Q
1+
#307
0+
#308
b10011010 Q
1+
0,
#309
0+
#310
b10011011 Q
1+
#311
0+
#312
b1101100000 L
b1110100110 9
b1101000010 :
b1101110100 &
b1101110100 7
b1101110100 K
b10011100 Q
1+
b100111 R
1,
#313
0+
#314
b10011101 Q
1+
#315
0+
#316
b10011110 Q
1+
0,
#317
0+
#318
b10011111 Q
1+
#319
0+
#320
b1101001100 L
b1110010010 9
b1100101110 :
b1101100000 &
b1101100000 7
b1101100000 K
b10100000 Q
1+
b101000 R
1,
#321
0+
#322
b10100001 Q
1+
#323
0+
#324
b10100010 Q
1+
0,
#325
0+
#326
b10100011 Q
1+
#327
0+
#328
b1100111000 L
b1101111110 9
b1100011010 :
b1101001100 &
b1101001100 7
b1101001100 K
b10100100 Q
1+
b101001 R
1,
#329
0+
#330
b10100101 Q
1+
#331
0+
#332
b10100110 Q
1+
0,
#333
0+
#334
b10100111 Q
1+
#335
0+
#336
b1100100100 L
b1101101010 9
b1100000110 :
b1100111000 &
b1100111000 7
b1100111000 K
b10101000 Q
1+
b101010 R
1,
#337
0+
#338
b10101001 Q
1+
#339
0+
#340
b10101010 Q
1+
0,
#341
0+
#342
b10101011 Q
1+
#343
0+
#344
b1100010000 L
b1101010110 9
b1011110010 :
b1100100100 &
b1100100100 7
b1100100100 K
b10101100 Q
1+
b101011 R
1,
#345
0+
#346
b10101101 Q
1+
#347
0+
#348
b10101110 Q
1+
0,
#349
0+
#350
b10101111 Q
1+
#351
0+
#352
b1011111100 L
b1101000010 9
b1011011110 :
b1100010000 &
b1100010000 7
b1100010000 K
b10110000 Q
1+
b101100 R
1,
#353
0+
#354
b10110001 Q
1+
#355
0+
#356
b10110010 Q
1+
0,
#357
0+
#358
b10110011 Q
1+
#359
0+
#360
b1011101000 L
b1100101110 9
b1011001010 :
b1011111100 &
b1011111100 7
b1011111100 K
b10110100 Q
1+
b101101 R
1,
#361
0+
#362
b10110101 Q
1+
#363
0+
#364
b10110110 Q
1+
0,
#365
0+
#366
b10110111 Q
1+
#367
0+
#368
b1011010100 L
b1100011010 9
b1010110110 :
b1011101000 &
b1011101000 7
b1011101000 K
b10111000 Q
1+
b101110 R
1,
#369
0+
#370
b10111001 Q
1+
#371
0+
#372
b10111010 Q
1+
0,
#373
0+
#374
b10111011 Q
1+
#375
0+
#376
b1011000000 L
b1100000110 9
b1010100010 :
b1011010100 &
b1011010100 7
b1011010100 K
b10111100 Q
1+
b101111 R
1,
#377
0+
#378
b10111101 Q
1+
#379
0+
#380
b10111110 Q
1+
0,
#381
0+
#382
b10111111 Q
1+
#383
0+
#384
b1010101100 L
b1011110010 9
b1010001110 :
b1011000000 &
b1011000000 7
b1011000000 K
b11000000 Q
1+
b110000 R
1,
#385
0+
#386
b11000001 Q
1+
#387
0+
#388
b11000010 Q
1+
0,
#389
0+
#390
b11000011 Q
1+
#391
0+
#392
b1010011000 L
b1011011110 9
b1001111010 :
b1010101100 &
b1010101100 7
b1010101100 K
b11000100 Q
1+
b110001 R
1,
#393
0+
#394
b11000101 Q
1+
#395
0+
#396
b11000110 Q
1+
0,
#397
0+
#398
b11000111 Q
1+
#399
0+
#400
b1010000100 L
b1011001010 9
b1001100110 :
b1010011000 &
b1010011000 7
b1010011000 K
b11001000 Q
1+
b110010 R
1,
#401
0+
#402
b11001001 Q
1+
#403
0+
#404
b11001010 Q
1+
0,
#405
0+
#406
b11001011 Q
1+
#407
0+
#408
b1001110000 L
b1010110110 9
b1001010010 :
b1010000100 &
b1010000100 7
b1010000100 K
b11001100 Q
1+
b110011 R
1,
#409
0+
#410
b11001101 Q
1+
#411
0+
#412
b11001110 Q
1+
0,
#413
0+
#414
b11001111 Q
1+
#415
0+
#416
b1001011100 L
b1010100010 9
b1000111110 :
b1001110000 &
b1001110000 7
b1001110000 K
b11010000 Q
1+
b110100 R
1,
#417
0+
#418
b11010001 Q
1+
#419
0+
#420
b11010010 Q
1+
0,
#421
0+
#422
b11010011 Q
1+
#423
0+
#424
b1001001000 L
b1010001110 9
b1000101010 :
b1001011100 &
b1001011100 7
b1001011100 K
b11010100 Q
1+
b110101 R
1,
#425
0+
#426
b11010101 Q
1+
#427
0+
#428
b11010110 Q
1+
0,
#429
0+
#430
b11010111 Q
1+
#431
0+
#432
b1000110100 L
b1001111010 9
b1000010110 :
b1001001000 &
b1001001000 7
b1001001000 K
b11011000 Q
1+
b110110 R
1,
#433
0+
#434
b11011001 Q
1+
#435
0+
#436
b11011010 Q
1+
0,
#437
0+
#438
b11011011 Q
1+
#439
0+
#440
b1000100000 L
b1001100110 9
b1000000010 :
b1000110100 &
b1000110100 7
b1000110100 K
b11011100 Q
1+
b110111 R
1,
#441
0+
#442
b11011101 Q
1+
#443
0+
#444
b11011110 Q
1+
0,
#445
0+
#446
b11011111 Q
1+
#447
0+
#448
b1000001100 L
b1001010010 9
b111101110 :
b1000100000 &
b1000100000 7
b1000100000 K
b11100000 Q
1+
b111000 R
1,
#449
0+
#450
b11100001 Q
1+
#451
0+
#452
b11100010 Q
1+
0,
#453
0+
#454
b11100011 Q
1+
#455
0+
#456
b111111000 L
b1000111110 9
b111011010 :
b1000001100 &
b1000001100 7
b1000001100 K
b11100100 Q
1+
b111001 R
1,
#457
0+
#458
b11100101 Q
1+
#459
0+
#460
b11100110 Q
1+
0,
#461
0+
#462
b11100111 Q
1+
#463
0+
#464
b111100100 L
b1000101010 9
b111000110 :
b111111000 &
b111111000 7
b111111000 K
b11101000 Q
1+
b111010 R
1,
#465
0+
#466
b11101001 Q
1+
#467
0+
#468
b11101010 Q
1+
0,
#469
0+
#470
b11101011 Q
1+
#471
0+
#472
b111010000 L
b1000010110 9
b110110010 :
b111100100 &
b111100100 7
b111100100 K
b11101100 Q
1+
b111011 R
1,
#473
0+
#474
b11101101 Q
1+
#475
0+
#476
b11101110 Q
1+
0,
#477
0+
#478
b11101111 Q
1+
#479
0+
#480
b110111100 L
b1000000010 9
b110011110 :
b111010000 &
b111010000 7
b111010000 K
b11110000 Q
1+
b111100 R
1,
#481
0+
#482
b11110001 Q
1+
#483
0+
#484
b11110010 Q
1+
0,
#485
0+
#486
b11110011 Q
1+
#487
0+
#488
b110101000 L
b111101110 9
b110001010 :
b110111100 &
b110111100 7
b110111100 K
b11110100 Q
1+
b111101 R
1,
#489
0+
#490
b11110101 Q
1+
#491
0+
#492
b11110110 Q
1+
0,
#493
0+
#494
b11110111 Q
1+
#495
0+
#496
b110010100 L
b111011010 9
b101110110 :
b110101000 &
b110101000 7
b110101000 K
b11111000 Q
1+
b111110 R
1,
#497
0+
#498
b11111001 Q
1+
#499
0+
#500
b11111010 Q
1+
0,
#504
b110000000 L
b111000110 9
b101100010 :
b110010100 &
b110010100 7
b110010100 K
b111111 R
1,
#508
0,
#512
b101101100 L
b110110010 9
b101001110 :
b110000000 &
b110000000 7
b110000000 K
b1000000 R
1,
#516
0,
#520
b101011000 L
b110011110 9
b100111010 :
b101101100 &
b101101100 7
b101101100 K
b1000001 R
1,
#524
0,
#528
b101000100 L
b110001010 9
b100100110 :
b101011000 &
b101011000 7
b101011000 K
b1000010 R
1,
#532
0,
#536
b100110000 L
b101110110 9
b100010010 :
b101000100 &
b101000100 7
b101000100 K
b1000011 R
1,
#540
0,
#544
b100011100 L
b101100010 9
b11111110 :
b100110000 &
b100110000 7
b100110000 K
b1000100 R
1,
#548
0,
#552
b100001000 L
b101001110 9
b11101010 :
b100011100 &
b100011100 7
b100011100 K
b1000101 R
1,
#556
0,
#560
b11110100 L
b100111010 9
b11010110 :
b100001000 &
b100001000 7
b100001000 K
b1000110 R
1,
#564
0,
#568
b11100000 L
b100100110 9
b11000010 :
b11110100 &
b11110100 7
b11110100 K
b1000111 R
1,
#572
0,
#576
b11001100 L
b100010010 9
b10101110 :
b11100000 &
b11100000 7
b11100000 K
b1001000 R
1,
#580
0,
#584
b10111000 L
b11111110 9
b10011010 :
b11001100 &
b11001100 7
b11001100 K
b1001001 R
1,
#588
0,
#592
b10100100 L
b11101010 9
b10000110 :
b10111000 &
b10111000 7
b10111000 K
b1001010 R
1,
#596
0,
#600
b10010000 L
b11010110 9
b1110010 :
b10100100 &
b10100100 7
b10100100 K
b1001011 R
1,
#604
0,
#608
b1111100 L
b11000010 9
b1011110 :
b10010000 &
b10010000 7
b10010000 K
b1001100 R
1,
#612
0,
#616
b1101000 L
b10101110 9
b1001010 :
b1111100 &
b1111100 7
b1111100 K
b1001101 R
1,
#620
0,
#624
b1010100 L
b10011010 9
b110110 :
b1101000 &
b1101000 7
b1101000 K
b1001110 R
1,
#628
0,
#632
b1000000 L
b10000110 9
b100010 :
b1010100 &
b1010100 7
b1010100 K
b1001111 R
1,
#636
0,
#640
b101100 L
b1110010 9
b1110 :
b1000000 &
b1000000 7
b1000000 K
b1010000 R
1,
#644
0,
#648
b11000 L
b1011110 9
b1111111010 :
b101100 &
b101100 7
b101100 K
b1010001 R
1,
#652
0,
#656
b100 L
b1001010 9
b1111100110 :
b11000 &
b11000 7
b11000 K
b1010010 R
1,
#660
0,
#664
b1111110000 L
b110110 9
b1111010010 :
b100 &
b100 7
b100 K
b1010011 R
1,
#668
0,
#672
b1111011100 L
b100010 9
b1110111110 :
b1111110000 &
b1111110000 7
b1111110000 K
b1010100 R
1,
#676
0,
#680
b1111001000 L
b1110 9
b1110101010 :
b1111011100 &
b1111011100 7
b1111011100 K
b1010101 R
1,
#684
0,
#688
b1110110100 L
b1111111010 9
b1110010110 :
b1111001000 &
b1111001000 7
b1111001000 K
b1010110 R
1,
#692
0,
#696
b1110100000 L
b1111100110 9
b1110000010 :
b1110110100 &
b1110110100 7
b1110110100 K
b1010111 R
1,
#700
0,
#704
b1110001100 L
b1111010010 9
b1101101110 :
b1110100000 &
b1110100000 7
b1110100000 K
b1011000 R
1,
#708
0,
#712
b1101111000 L
b1110111110 9
b1101011010 :
b1110001100 &
b1110001100 7
b1110001100 K
b1011001 R
1,
#716
0,
#720
b1101100100 L
b1110101010 9
b1101000110 :
b1101111000 &
b1101111000 7
b1101111000 K
b1011010 R
1,
#724
0,
#728
b1101010000 L
b1110010110 9
b1100110010 :
b1101100100 &
b1101100100 7
b1101100100 K
b1011011 R
1,
#732
0,
#736
b1100111100 L
b1110000010 9
b1100011110 :
b1101010000 &
b1101010000 7
b1101010000 K
b1011100 R
1,
#740
0,
#744
b1100101000 L
b1101101110 9
b1100001010 :
b1100111100 &
b1100111100 7
b1100111100 K
b1011101 R
1,
#748
0,
#752
b1100010100 L
b1101011010 9
b1011110110 :
b1100101000 &
b1100101000 7
b1100101000 K
b1011110 R
1,
#756
0,
#760
b1100000000 L
b1101000110 9
b1011100010 :
b1100010100 &
b1100010100 7
b1100010100 K
b1011111 R
1,
#764
0,
#768
b1011101100 L
b1100110010 9
b1011001110 :
b1100000000 &
b1100000000 7
b1100000000 K
b1100000 R
1,
#772
0,
#776
b1011011000 L
b1100011110 9
b1010111010 :
b1011101100 &
b1011101100 7
b1011101100 K
b1100001 R
1,
#780
0,
#784
b1011000100 L
b1100001010 9
b1010100110 :
b1011011000 &
b1011011000 7
b1011011000 K
b1100010 R
1,
#788
0,
